README.md
setup.cfg
setup.py
delairstack/__init__.py
delairstack/sdk.py
delairstack/apis/__init__.py
delairstack/apis/provider.py
delairstack/apis/client/__init__.py
delairstack/apis/client/analytics/__init__.py
delairstack/apis/client/analytics/analyticsimpl.py
delairstack/apis/client/analytics/productsimpl.py
delairstack/apis/client/annotations/__init__.py
delairstack/apis/client/annotations/annotationsimpl.py
delairstack/apis/client/auth/__init__.py
delairstack/apis/client/auth/sharetokensimpl.py
delairstack/apis/client/comments/__init__.py
delairstack/apis/client/comments/commentsimpl.py
delairstack/apis/client/datamngt/__init__.py
delairstack/apis/client/datamngt/datasetsimpl.py
delairstack/apis/client/externalproviders/__init__.py
delairstack/apis/client/externalproviders/credentialsimpl.py
delairstack/apis/client/projectmngt/__init__.py
delairstack/apis/client/projectmngt/flightsimpl.py
delairstack/apis/client/projectmngt/missionsimpl.py
delairstack/apis/client/projectmngt/projectsimpl.py
delairstack/apis/client/tags/__init__.py
delairstack/apis/client/tags/tagsimpl.py
delairstack/core/__init__.py
delairstack/core/config.py
delairstack/core/errors.py
delairstack/core/connection/__init__.py
delairstack/core/connection/abstract_connection.py
delairstack/core/connection/async_connection.py
delairstack/core/connection/connection.py
delairstack/core/connection/credentials.py
delairstack/core/connection/token.py
delairstack/core/resources/__init__.py
delairstack/core/resources/annotations.py
delairstack/core/resources/auth.py
delairstack/core/resources/comments.py
delairstack/core/resources/credentials.py
delairstack/core/resources/resource.py
delairstack/core/resources/resources_manager_base.py
delairstack/core/resources/tags.py
delairstack/core/resources/analytics/__init__.py
delairstack/core/resources/analytics/analytics.py
delairstack/core/resources/analytics/products.py
delairstack/core/resources/datamngt/__init__.py
python_delairstack.egg-info/PKG-INFO
python_delairstack.egg-info/SOURCES.txt
python_delairstack.egg-info/dependency_links.txt
python_delairstack.egg-info/requires.txt
python_delairstack.egg-info/top_level.txt