Metadata-Version: 2.1
Name: python-delairstack
Version: 1.7.9
Summary: High-level Python interface to Delair.ai API
Home-page: https://github.com/delair-ai/python-delairstack
Author: Delair.ai Backend Team
Author-email: backend-team@delair.aero
License: MIT
Keywords: sdk delair delair.ai
Platform: UNKNOWN
Classifier: Development Status :: 5 - Production/Stable
Classifier: Intended Audience :: Developers
Classifier: Topic :: Software Development :: Build Tools
Classifier: License :: OSI Approved :: MIT License
Classifier: Programming Language :: Python :: 3
Classifier: Programming Language :: Python :: 3.4
Classifier: Programming Language :: Python :: 3.5
Classifier: Programming Language :: Python :: 3.6
Classifier: Programming Language :: Python :: 3.7
Provides-Extra: development
Provides-Extra: coverage
Provides-Extra: documentation
Provides-Extra: tests
